README.md
setup.cfg
setup.py
carte_blanche_path/__init__.py
carte_blanche_path.egg-info/PKG-INFO
carte_blanche_path.egg-info/SOURCES.txt
carte_blanche_path.egg-info/dependency_links.txt
carte_blanche_path.egg-info/not-zip-safe
carte_blanche_path.egg-info/top_level.txt