Metadata-Version: 1.0
Name: carte-blanche-path
Version: 1.1.0
Summary: A utility for setting project root directory
Home-page: https://github.com/huffmsa/carte-blanche-path
Author: Sam Huffman
Author-email: huffmsa@gmail.com
License: MIT
Platform: UNKNOWN
